oci_squash/__init__.py
oci_squash/__main__.py
oci_squash/archive.py
oci_squash/cli.py
oci_squash/detector.py
oci_squash/errors.py
oci_squash/formats.py
oci_squash/metadata.py
oci_squash/requirements.txt
oci_squash/squash.py
oci_squash/utils.py
oci_squash-0.1.0.dist-info/METADATA
oci_squash-0.1.0.dist-info/WHEEL
oci_squash-0.1.0.dist-info/entry_points.txt
oci_squash-0.1.0.dist-info/licenses/LICENSE
oci_squash-0.1.0.dist-info/RECORD
