Metadata-Version: 2.4
Name: oci-squash
Version: 0.1.0
Summary: OCI/Docker image tar layer squashing tool (pure Python stdlib)
Author: lyonv
License: MIT License
License-File: LICENSE
Classifier: Environment :: Console
Classifier: License :: OSI Approved :: MIT License
Classifier: Programming Language :: Python :: 3
Classifier: Programming Language :: Python :: 3 :: Only
Classifier: Topic :: System :: Archiving
Requires-Python: >=3.8
